__init__.py
powerful_toolkit/IO_test.py
powerful_toolkit/__init__.py
powerful_toolkit/data_structures.py
powerful_toolkit/random_anything.py
powerful_toolkit-0.1.0.dist-info/METADATA
powerful_toolkit-0.1.0.dist-info/WHEEL
powerful_toolkit-0.1.0.dist-info/top_level.txt
powerful_toolkit-0.1.0.dist-info/RECORD
