Metadata-Version: 2.4
Name: powerful_toolkit
Version: 0.1.0
Summary: A toolkit.
Author-email: Gopa <36851252@qq.com>
Requires-Python: >=3.11
